PaperlogicSDK/service.cpython-39-darwin.so
PaperlogicSDK/sign.cpython-39-darwin.so
PaperlogicSDK/__init__.py
PaperlogicSDK/imprint.py
PaperlogicSDK/timestamp.cpython-39-darwin.so
PaperlogicSDK/PaperlogicSign/__init__.py
PaperlogicSDK/PaperlogicSign/paperlogic_signature/__init__.py
PaperlogicSDK/PaperlogicSign/paperlogic_signature/generated/xml.py
PaperlogicSDK/PaperlogicSign/paperlogic_signature/generated/__init__.py
PaperlogicSDK/PaperlogicSign/paperlogic_signature/generated/py.typed
PaperlogicSDK/PaperlogicSign/paperlogic_signature/generated/w3c/__init__.py
PaperlogicSDK/PaperlogicSign/paperlogic_signature/generated/w3c/xmldsig_core.py
PaperlogicSDK/PaperlogicSign/paperlogic_signature/generated/etsi/xades.py
PaperlogicSDK/PaperlogicSign/paperlogic_signature/generated/etsi/ts_119612.py
PaperlogicSDK/PaperlogicSign/paperlogic_signature/generated/etsi/__init__.py
PaperlogicSDK/PaperlogicSign/paperlogic_signature/generated/etsi/ts_119612_sie.py
PaperlogicSDK/PaperlogicSign/paperlogic_signature/generated/etsi/ts_11910202.py
PaperlogicSDK/PaperlogicSign/paperlogic_signature/generated/etsi/ts_119612_extra.py
PaperlogicSDK/PaperlogicSign/paperlogic_signature/config/local_keys.py
PaperlogicSDK/PaperlogicSign/paperlogic_signature/config/logging.py
PaperlogicSDK/PaperlogicSign/paperlogic_signature/config/__init__.py
PaperlogicSDK/PaperlogicSign/paperlogic_signature/config/api.py
PaperlogicSDK/PaperlogicSign/paperlogic_signature/config/pkcs11.py
PaperlogicSDK/PaperlogicSign/paperlogic_signature/config/py.typed
PaperlogicSDK/PaperlogicSign/paperlogic_signature/config/errors.py
PaperlogicSDK/PaperlogicSign/paperlogic_signature/version/__init__.py
PaperlogicSDK/PaperlogicSign/paperlogic_signature/version/py.typed
PaperlogicSDK/PaperlogicSign/paperlogic_signature/stamp/functions.py
PaperlogicSDK/PaperlogicSign/paperlogic_signature/stamp/__init__.py
PaperlogicSDK/PaperlogicSign/paperlogic_signature/stamp/qr.py
paperlogicsdk-1.0.38.dist-info/RECORD
paperlogicsdk-1.0.38.dist-info/WHEEL
paperlogicsdk-1.0.38.dist-info/entry_points.txt
paperlogicsdk-1.0.38.dist-info/top_level.txt
paperlogicsdk-1.0.38.dist-info/METADATA
