Metadata-Version: 2.1
Name: PaperlogicSDK
Version: 1.0.38
Summary: A Python SDK for digital document signing
Requires-Python: >=3.8
Requires-Dist: asn1crypto==1.5.1
Requires-Dist: uritools==4.0.3
Requires-Dist: oscrypto==1.3.0
Requires-Dist: tzlocal==5.2
Requires-Dist: pycryptodome==3.15.0
Requires-Dist: click==8.1.7
Requires-Dist: requests==2.32.3
Requires-Dist: cryptography==43.0.3
Requires-Dist: pytz==2023.3
Requires-Dist: python-pkcs11==0.7.0
Requires-Dist: pyhanko-certvalidator==0.29.0
Requires-Dist: Pillow==10.4.0
Requires-Dist: reportlab==4.0.4
Requires-Dist: PyPDF2==3.0.1
